RISC-V_MultiCycle/main_FSM.v
module main_FSM(
    input               clk,
                        reset,

    input [6:0]         op,
    
    output reg          AdrSrc,
                        MemWrite,
                        IRWrite,
    
    output reg [1:0]    ResultSrc,
    output reg [1:0]    ALUOp,
    output reg [1:0]    ALUSrcA,
                        ALUSrcB,
    output reg          RegWrite,
                        Branch, 
                        PCUpdate   
);

parameter   S0 = 0,
            S1 = 1,
            S2 = 2,
            S3 = 3,
            S4 = 4,
            S5 = 5,
            S6 = 6,
            S7 = 7,
            S8 = 8,
            S9 = 9,
            S10 = 10;

reg [3:0] current_state,next_state;

always @(posedge clk or posedge reset) begin
    if(reset) 
        current_state <= S0;
    else 
        current_state <= next_state;
end

always @(*)begin
    case(current_state)
    S0: 
        next_state = S1;
    S1:
        case(op)
            7'b0100011: next_state = S2; // sw
            7'b0000011: next_state = S2; // lw
            7'b0110011: next_state = S6; // R-type
            7'b0010011: next_state = S8; // I-type
            7'b1101111: next_state = S9; //JAL
            7'b1100011: next_state = S10; // beq
            default: next_state = S0;
        endcase

    S2: begin
        if(op == 7'b0100011) 
            next_state = S5; // sw
        else 
            next_state = S3; // lw
    end
    S3: 
        next_state = S4;
    S4: 
        next_state = S0;
    S5:
        next_state = S0;
    S6:
        next_state = S7;
    S7:
        next_state = S0;
    S8:
        next_state = S7;
    S9:
        next_state = S7;
    S10:
        next_state = S0;
    endcase 
end

always @(*) 
begin
    AdrSrc = 0;
    MemWrite = 0;
    IRWrite = 0;
    ResultSrc = 0;
    ALUOp = 0;
    ALUSrcA = 0;
    ALUSrcB = 0;
    RegWrite = 0;
    Branch = 0;
    PCUpdate = 0;
    
    case(current_state)
    S0: 
    begin
        AdrSrc = 0;
        IRWrite = 1;
        ALUSrcA = 2'b00;
        ALUSrcB = 2'b10;
        ALUOp = 2'b00;
        ResultSrc = 2'b10;
        PCUpdate = 1;
    end
    S1:
    begin
        ALUSrcA = 2'b01;
        ALUSrcB = 2'b01;
        ALUOp = 2'b00;
    end
    S2:
    begin
        ALUSrcA = 2'b10;
        ALUSrcB = 2'b01;
        ALUOp = 2'b00;
    end
    S3:
    begin
        ResultSrc = 2'b00;
        AdrSrc = 1;
    end
    S4:
    begin
        RegWrite = 1;
        ResultSrc = 2'b01;
    end
    S5:
    begin
        MemWrite = 1;
        AdrSrc = 1;
        ResultSrc = 2'b00;
    end
    S6:
    begin
        ALUSrcA = 2'b10;
        ALUSrcB = 2'b00;
        ALUOp = 2'b10;
    end
    S7:
    begin
        RegWrite = 1;
        ResultSrc = 2'b00;
    end
    S8:
    begin
        ALUSrcA = 2'b10;
        ALUSrcB = 2'b01;
        ALUOp = 2'b10;
    end
    S9:
    begin
        ALUSrcA = 2'b01;
        ALUSrcB = 2'b10;
        ALUOp = 2'b00;
        ResultSrc = 2'b00;
        PCUpdate = 1;
    end
    S10:
    begin
        ALUSrcA = 2'b10;
        ALUSrcB = 2'b00;
        ALUOp = 2'b01;
        Branch = 1;
        ResultSrc = 2'b00;
    end
    endcase
end

endmodule

RISC-V_MultiCycle/main_FSM_tb.v
module main_FSM_tb();

reg clk, reset;
reg [6:0] op;
wire AdrSrc, MemWrite, IRWrite;
wire [1:0] ResultSrc, ALUOp, ALUSrcA,ALUSrcB;
wire RegWrite, Branch, PCUpdate;

main_FSM uut (
    .clk(clk),
    .reset(reset),
    .op(op),
    .AdrSrc(AdrSrc),
    .MemWrite(MemWrite),
    .IRWrite(IRWrite),
    .ResultSrc(ResultSrc),
    .ALUOp(ALUOp),
    .ALUSrcA(ALUSrcA),
    .ALUSrcB(ALUSrcB),
    .RegWrite(RegWrite),
    .Branch(Branch),
    .PCUpdate(PCUpdate)
);

initial begin
    forever #5 clk = ~clk; // 10 time units period
end


initial begin
    // Initialize signals
    clk = 0;
    reset = 1;
    op = 7'b0000000; // NOP

    // Release reset after some time
    #10 reset = 0;

    // Test sequence for different instructions
    #10 op = 7'b0110011; // R-type
    #10;
    wait(uut.current_state == uut.S0); // Wait for R-type state
    #10 op = 7'b0010011; // I-type
    #10;
    wait(uut.current_state == uut.S0); // Wait for R-type state
    #10 op = 7'b0000011; // Load
    #10;
    wait(uut.current_state == uut.S0); // Wait for R-type state
    #10 op = 7'b0100011; // Store
    #10;
    wait(uut.current_state == uut.S0); // Wait for R-type state
    #10 op = 7'b1100011; // Branch
    #10;
    wait(uut.current_state == uut.S0); // Wait for R-type state

    // Finish simulation after some time
    #100 $finish;
end

initial 
begin
    $monitor("Time: %0t | State: %0d | op: %b | AdrSrc: %b | MemWrite: %b | IRWrite: %b | ResultSrc: %b | ALUOp: %b | ALUSrcA: %b | ALUSrcB: %b | RegWrite: %b | Branch: %b | PCUpdate: %b", 
             $time, uut.current_state, op, AdrSrc, MemWrite, IRWrite, ResultSrc, ALUOp, ALUSrcA, ALUSrcB, RegWrite, Branch, PCUpdate);    
end

initial begin
    $dumpfile("main_FSM_tb.vcd");
    $dumpvars(0, main_FSM_tb);
end

endmodule

RISC-V_MultiCycle/main_FSM_tb.vcd
$date
	Wed May 27 16:29:00 2026
$end
$version
	Icarus Verilog
$end
$timescale
	1s
$end
$scope module main_FSM_tb $end
$var wire 2 ! ResultSrc [1:0] $end
$var wire 1 " RegWrite $end
$var wire 1 # PCUpdate $end
$var wire 1 $ MemWrite $end
$var wire 1 % IRWrite $end
$var wire 1 & Branch $end
$var wire 1 ' AdrSrc $end
$var wire 2 ( ALUSrcB [1:0] $end
$var wire 2 ) ALUSrcA [1:0] $end
$var wire 2 * ALUOp [1:0] $end
$var reg 1 + clk $end
$var reg 7 , op [6:0] $end
$var reg 1 - reset $end
$scope module uut $end
$var wire 1 + clk $end
$var wire 7 . op [6:0] $end
$var wire 1 - reset $end
$var parameter 32 / S0 $end
$var parameter 32 0 S1 $end
$var parameter 32 1 S10 $end
$var parameter 32 2 S2 $end
$var parameter 32 3 S3 $end
$var parameter 32 4 S4 $end
$var parameter 32 5 S5 $end
$var parameter 32 6 S6 $end
$var parameter 32 7 S7 $end
$var parameter 32 8 S8 $end
$var parameter 32 9 S9 $end
$var reg 2 : ALUOp [1:0] $end
$var reg 2 ; ALUSrcA [1:0] $end
$var reg 2 < ALUSrcB [1:0] $end
$var reg 1 ' AdrSrc $end
$var reg 1 & Branch $end
$var reg 1 % IRWrite $end
$var reg 1 $ MemWrite $end
$var reg 1 # PCUpdate $end
$var reg 1 " RegWrite $end
$var reg 2 = ResultSrc [1:0] $end
$var reg 4 > current_state [3:0] $end
$var reg 4 ? next_state [3:0] $end
$upscope $end
$upscope $end
$enddefinitions $end
$comment Show the parameter values. $end
$dumpall
b1001 9
b1000 8
b111 7
b110 6
b101 5
b100 4
b11 3
b10 2
b1010 1
b1 0
b0 /
$end
#0
$dumpvars
b1 ?
b0 >
b10 =
b10 <
b0 ;
b0 :
b0 .
1-
b0 ,
0+
b0 *
b0 )
b10 (
0'
0&
1%
0$
1#
0"
b10 !
$end
#5
1+
#10
0+
0-
#15
b1 )
b1 ;
0#
b1 (
b1 <
b0 !
b0 =
0%
b0 ?
b1 >
1+
#20
b110 ?
0+
b110011 ,
b110011 .
#25
b10 *
b10 :
b0 (
b0 <
b10 )
b10 ;
b111 ?
b110 >
1+
#30
0+
#35
1"
b0 )
b0 ;
b0 *
b0 :
b0 ?
b111 >
1+
#40
0+
#45
1#
b10 !
b10 =
b10 (
b10 <
1%
0"
b1 ?
b0 >
1+
#50
0+
#55
b1 )
b1 ;
0#
b1 (
b1 <
b0 !
b0 =
0%
b1000 ?
b1 >
1+
b10011 ,
b10011 .
#60
0+
#65
b10 *
b10 :
b1 (
b1 <
b10 )
b10 ;
b111 ?
b1000 >
1+
#70
0+
#75
1"
b0 (
b0 <
b0 )
b0 ;
b0 *
b0 :
b0 ?
b111 >
1+
#80
0+
#85
1#
b10 !
b10 =
b10 (
b10 <
1%
0"
b1 ?
b0 >
1+
#90
0+
#95
b1 )
b1 ;
0#
b1 (
b1 <
b0 !
b0 =
0%
b10 ?
b1 >
1+
b11 ,
b11 .
#100
0+
#105
b1 (
b1 <
b10 )
b10 ;
b11 ?
b10 >
1+
#110
0+
#115
1'
b0 (
b0 <
b0 )
b0 ;
b100 ?
b11 >
1+
#120
0+
#125
b1 !
b1 =
1"
0'
b0 ?
b100 >
1+
#130
0+
#135
1#
b10 (
b10 <
1%
0"
b10 !
b10 =
b1 ?
b0 >
1+
#140
0+
#145
b1 )
b1 ;
0#
b1 (
b1 <
b0 !
b0 =
0%
b10 ?
b1 >
1+
b100011 ,
b100011 .
#150
0+
#155
b1 (
b1 <
b10 )
b10 ;
b101 ?
b10 >
1+
#160
0+
#165
1'
1$
b0 (
b0 <
b0 )
b0 ;
b0 ?
b101 >
1+
#170
0+
#175
1#
b10 !
b10 =
b10 (
b10 <
1%
0$
0'
b1 ?
b0 >
1+
#180
0+
#185
b1 )
b1 ;
0#
b1 (
b1 <
b0 !
b0 =
0%
b1010 ?
b1 >
1+
b1100011 ,
b1100011 .
#190
0+
#195
1&
b1 *
b1 :
b0 (
b0 <
b10 )
b10 ;
b0 ?
b1010 >
1+
#200
0+
#205
1#
b10 !
b10 =
b10 (
b10 <
1%
0&
b0 )
b0 ;
b0 *
b0 :
b1 ?
b0 >
1+
#210
0+
#215
b1 )
b1 ;
0#
b1 (
b1 <
b0 !
b0 =
0%
b1010 ?
b1 >
1+
#220
0+
#225
1&
b1 *
b1 :
b0 (
b0 <
b10 )
b10 ;
b0 ?
b1010 >
1+
#230
0+
#235
1#
b10 !
b10 =
b10 (
b10 <
1%
0&
b0 )
b0 ;
b0 *
b0 :
b1 ?
b0 >
1+
#240
0+
#245
b1 )
b1 ;
0#
b1 (
b1 <
b0 !
b0 =
0%
b1010 ?
b1 >
1+
#250
0+
#255
1&
b1 *
b1 :
b0 (
b0 <
b10 )
b10 ;
b0 ?
b1010 >
1+
#260
0+
#265
1#
b10 !
b10 =
b10 (
b10 <
1%
0&
b0 )
b0 ;
b0 *
b0 :
b1 ?
b0 >
1+
#270
0+
#275
b1 )
b1 ;
0#
b1 (
b1 <
b0 !
b0 =
0%
b1010 ?
b1 >
1+
#280
0+
#285
1&
b1 *
b1 :
b0 (
b0 <
b10 )
b10 ;
b0 ?
b1010 >
1+
#290
0+
#295
1#
b10 !
b10 =
b10 (
b10 <
1%
0&
b0 )
b0 ;
b0 *
b0 :
b1 ?
b0 >
1+
#300
0+
#305
b1 )
b1 ;
0#
b1 (
b1 <
b0 !
b0 =
0%
b1010 ?
b1 >
1+
